{
  "name": "Course Page",
  "path": "/course/:slug",
  "sections": [
    {
      "__resolveType": "HeaderLateral - Geral"
    },
    {
      "__resolveType": "site/sections/ContainerContent.tsx",
      "sections": [
        {
          "section": {
            "__resolveType": "site/sections/CoursePage.tsx",
            "course": {
              "sections": [],
              "details": [],
              "courseIncludes": [],
              "individualCourse": {
                "difficulty": "Iniciante",
                "category": "Desenvolvimento"
              },
              "tabsCourse": []
            }
          }
        }
      ]
    }
  ],
  "seo": {
    "__resolveType": "website/sections/Seo/SeoV2.tsx"
  },
  "__resolveType": "website/pages/Page.tsx"
}